pypsupertime/__init__.py
pypsupertime/model.py
pypsupertime/parameter_search.py
pypsupertime/plots.py
pypsupertime/preprocessing.py
pypsupertime/psupertime.py
pypsupertime-2.2.2.dist-info/WHEEL
pypsupertime-2.2.2.dist-info/METADATA
pypsupertime-2.2.2.dist-info/RECORD
