Metadata-Version: 2.1
Name: pypsupertime
Version: 2.2.2
Summary: PyPsupertime
Author-email: Julian Flesch <julian.flesch@student.uni-tuebingen.de>
Requires-Python: >=3.8
Classifier: Programming Language :: Python :: 3
Classifier: License :: OSI Approved :: MIT License
Classifier: Operating System :: OS Independent
Requires-Dist: numpy
Requires-Dist: matplotlib
Requires-Dist: seaborn
Requires-Dist: scikit-learn
Requires-Dist: scipy
Requires-Dist: scanpy
Requires-Dist: anndata
Requires-Dist: torch
Project-URL: API Documentation, https://pypsupertime.readthedocs.io/en/latest/
Project-URL: Bug Tracker, https://github.com/claassenlab/pyPsupertime/issues
Project-URL: Source, https://github.com/claassenlab/PyPsupertime
